xrootdfs/__init__.py
xrootdfs/env.py
xrootdfs/fs.py
xrootdfs/opener.py
xrootdfs/utils.py
xrootdfs/version.py
xrootdfs/xrdfile.py
xrootdfs-0.1.0.dist-info/DESCRIPTION.rst
xrootdfs-0.1.0.dist-info/METADATA
xrootdfs-0.1.0.dist-info/metadata.json
xrootdfs-0.1.0.dist-info/RECORD
xrootdfs-0.1.0.dist-info/top_level.txt
xrootdfs-0.1.0.dist-info/WHEEL
