Metadata-Version: 2.0
Name: xrootdfs
Version: 0.1.0
Summary: XRootDFS is PyFilesystem interface to XRootD.
Home-page: http://github.com/inveniosoftware/xrootdfs/
Author: Invenio Collaboration
Author-email: info@invenio-software.org
License: BSD
Platform: any
Classifier: Programming Language :: Python :: 2
Classifier: Programming Language :: Python :: 2.7
Classifier: Development Status :: 5 - Production/Stable
Classifier: Intended Audience :: Developers
Classifier: License :: OSI Approved :: BSD License
Classifier: Topic :: Utilities
Requires-Dist: fs (>=0.4.0)
Requires-Dist: pyxrootd
